connect/__init__.py
connect/telegram_bot/__init__.py
connect/telegram_bot/bot.py
connect/telegram_bot/constants.py
connect/telegram_bot/decorators/__init__.py
connect/telegram_bot/decorators/chat_context.py
connect/telegram_bot/decorators/log_args.py
connect/telegram_bot/errors/__init__.py
connect/telegram_bot/errors/saved_filter_not_found.py
connect/telegram_bot/renderers/__init__.py
connect/telegram_bot/renderers/qs2md.py
connect/telegram_bot/telegram_conversation.py
connect_telegram_bot-1.0.1.dist-info/LICENSE
connect_telegram_bot-1.0.1.dist-info/WHEEL
connect_telegram_bot-1.0.1.dist-info/METADATA
connect_telegram_bot-1.0.1.dist-info/RECORD
