Metadata-Version: 2.1
Name: connect-telegram-bot
Version: 1.0.1
Summary: Connect Telegram Bot
Home-page: https://connect.cloudblue.com
License: Apache-2.0
Keywords: telegram,connect,utility,cloudblue,bot
Author: CloudBlue LLC
Requires-Python: >=3.8,<4.0
Classifier: Development Status :: 5 - Production/Stable
Classifier: Environment :: Console
Classifier: Intended Audience :: Developers
Classifier: License :: OSI Approved :: Apache Software License
Classifier: Operating System :: OS Independent
Classifier: Programming Language :: Python :: 3
Classifier: Programming Language :: Python :: 3.8
Classifier: Programming Language :: Python :: 3.9
Classifier: Topic :: Software Development :: Libraries
Classifier: Topic :: Utilities
Requires-Dist: django (==2.2.19)
Requires-Dist: python-telegram-bot (>=13.3,<14.0)
Project-URL: Repository, https://github.com/cloudblue/connect-telegram-bot
